{
    "no_wrap": true,
    "title": "時常熬夜……",
    "text_block_list": [
        {
            "name": "大鳴大放",
            "text": "搭載了AI的健身機器──\n根據收集到的數據來擬定有效率的訓練內容……\n嗯……"
        },
        {
            "name": "大鳴大放",
            "text": "……唔，已經這麼晚了。\n看完這一頁就該睡了──"
        },
        {
            "name": "大鳴大放",
            "text": "唔！AI會測量肌肉量，\n幫忙設定接近極限的強度啊。\n還有參考用的訓練影片。"
        },
        {
            "name": "大鳴大放",
            "text": "…………\n……再看一下下應該沒關係……"
        },
        {
            "name": "獨白",
            "text": "大鳴大放因為對最新訓練機器的好奇心，\n而不小心熬夜了……"
        }
    ]
}