{
    "no_wrap": true,
    "title": "競賽勝利",
    "text_block_list": [
        {
            "name": "玉藻十字",
            "text": "…………"
        },
        {
            "name": "玉藻十字",
            "text": "……太好了。\n這次……",
            "choice_data_list": [
                "恭喜妳拿到第1名"
            ]
        },
        {
            "name": "玉藻十字",
            "text": "……啊，對喔。\n訓練員。"
        },
        {
            "name": "玉藻十字",
            "text": "我……贏了呢。",
            "choice_data_list": [
                "辦個慶功宴吧",
                "……妳的表情完全沒有獲勝後的喜悅呢",
                "……妳的表情完全沒有獲勝後的喜悅呢"
            ]
        },
        {
            "name": "玉藻十字",
            "text": "我……贏了呢。",
            "choice_data_list": [
                "辦個慶功宴吧",
                "……妳的表情完全沒有獲勝後的喜悅呢",
                "……妳的表情完全沒有獲勝後的喜悅呢"
            ]
        },
        {
            "name": "玉藻十字",
            "text": "……哈哈，好耶。\n熱鬧地辦一場吧。"
        },
        {
            "name": "玉藻十字",
            "text": "這樣我心情也會比較輕鬆……"
        },
        {
            "name": "玉藻十字",
            "text": "……！！\n………………唔。",
            "choice_data_list": [
                "怎麼了？",
                "怎麼了嗎？"
            ]
        },
        {
            "name": "玉藻十字",
            "text": "我剛剛說了……「心情會比較輕鬆」嗎？\n我明明獲勝了，明明跑贏了。怎麼會……"
        },
        {
            "name": "玉藻十字",
            "text": "……"
        },
        {
            "name": "玉藻十字",
            "text": "訓練員，抱歉。\n慶功宴……還是下次再說吧。"
        },
        {
            "name": "玉藻十字",
            "text": "啊，但只是暫時「延期」喔。\n等正式辦的那天，\n我會連今天的份一起用力慶祝的。"
        },
        {
            "name": "玉藻十字",
            "text": "……所以，\n到時候就麻煩你囉，訓練員。"
        },
        {
            "name": "獨白",
            "text": "為了能夠迎接盡情慶祝的那天，\n我收下了玉藻十字的誓言。"
        },
        {
            "name": "玉藻十字",
            "text": "……唔！"
        },
        {
            "name": "玉藻十字",
            "text": "……啊、啊哈哈。\n對啊，你說得沒錯……！"
        },
        {
            "name": "玉藻十字",
            "text": "現在比起獲勝，\n我滿腦子都是平安跑完的事情……"
        },
        {
            "name": "玉藻十字",
            "text": "……到底為什麼會這樣。\n我明明必須更有自信、更開心才行的……！"
        },
        {
            "name": "玉藻十字",
            "text": "怎麼能只是跑完全程就滿足……！\n以後還會有更多、更激烈的比賽\n在等著我的說……！"
        },
        {
            "name": "獨白",
            "text": "……不曉得這是她對自己的憤怒，或者是悲哀。"
        },
        {
            "name": "獨白",
            "text": "在休息室裡因悔恨而擅抖不已的玉藻十字，\n決心將這份能量帶到下一場比賽中。"
        }
    ]
}