{
    "no_wrap": true,
    "title": "1週年紀念③　～然後，掀起陣風～",
    "text_block_list": [
        {
            "name": "三人",
            "text": "呼、呼、呼、呼──！！"
        },
        {
            "name": "目白阿爾丹",
            "text": "（我要就這樣領先到最後──！）"
        },
        {
            "name": "八重無敵",
            "text": "（才不會讓妳得逞！我要從外圍超過妳──！）"
        },
        {
            "name": "櫻花千代王",
            "text": "唔……唔、唔唔唔唔唔～……！！"
        },
        {
            "name": "丸善斯基",
            "text": "──……"
        },
        {
            "name": "丸善斯基",
            "text": "千代……妳還可以再更快吧？"
        },
        {
            "name": "櫻花千代王",
            "text": "！！\n……喝啊啊啊啊啊啊啊啊啊！！"
        },
        {
            "name": "阿爾丹＆八重",
            "text": "──……！！"
        },
        {
            "name": "櫻花千代王",
            "text": "呼、呼、呼、呼──！！"
        },
        {
            "name": "目白阿爾丹",
            "text": "唔……太意外了。\n沒想到竟然可以從那個位置超前過來……"
        },
        {
            "name": "八重無敵",
            "text": "就是……說啊。太強了──"
        },
        {
            "name": "八重無敵",
            "text": "真的太強了……就是這樣才更讓人熱血沸騰……！\n呵，呵呵呵呵呵呵……！！"
        },
        {
            "name": "目白阿爾丹",
            "text": "……八重？"
        },
        {
            "name": "八重無敵",
            "text": "啊，沒事！！──咳咳。\n感謝兩位一大早就陪我相互切磋。"
        },
        {
            "name": "櫻花千代王",
            "text": "啊──嗯，彼、彼此彼此……！呼。\n真的很謝謝妳們……！"
        },
        {
            "name": "目白阿爾丹",
            "text": "我也要謝謝兩位。\n……妳們讓我清楚找出了自己現在的實力在哪裡。"
        },
        {
            "name": "目白阿爾丹",
            "text": "我要再繼續一步步……往前走才行。"
        },
        {
            "name": "目白阿爾丹",
            "text": "然後，總有一天──"
        },
        {
            "name": "千代王&八重",
            "text": "……！"
        },
        {
            "name": "小栗帽",
            "text": "…………特雷森學園果然很棒。"
        },
        {
            "name": "小栗帽",
            "text": "太棒了……有好多值得競爭的對手。\n真的好多……！"
        },
        {
            "name": "玉藻十字",
            "text": "喔，怎麼啦？妳平常明明都一臉傻呼呼的，\n怎麼突然這麼熱血？"
        },
        {
            "name": "玉藻十字",
            "text": "那不然我再幫妳添點柴火吧。\n──要不要再並行練跑一次啊？小栗。"
        },
        {
            "name": "小栗帽",
            "text": "好啊……！\n我不會跑輸妳的。"
        },
        {
            "name": "小栗帽",
            "text": "我不會輸。不論對手是誰……就算對手是妳，我也絕不會輸！"
        },
        {
            "name": "玉藻十字",
            "text": "哈！妳這笑話還真好笑──我一定會跑贏妳。"
        },
        {
            "name": "丸善斯基",
            "text": "啊～真是的♪\n……大家都好可愛喔。"
        },
        {
            "name": "千明代表",
            "text": "嗯、嗯！──那，丸善妳只打算在旁邊看嗎？"
        },
        {
            "name": "丸善斯基",
            "text": "哎呀，是小千啊！早呀～\n嗯？可是妳自己不也是穿著制服嗎？"
        },
        {
            "name": "千明代表",
            "text": "沒有什麼衣服是穿了就不能跑步的。\n只要我們想跑，隨時都能跑，對吧？"
        },
        {
            "name": "丸善斯基",
            "text": "討厭啦，妳真的好熱情！\n被妳這樣一講，我也忍不住想跑了～……"
        },
        {
            "name": "丸善斯基",
            "text": "──不對，看來還是不能跑。\n被「皇帝」這樣瞪著怪可怕的～"
        },
        {
            "name": "魯道夫象徵",
            "text": "哈哈。妳們如此氣宇軒昂是好事，\n但也別忘了自己必須成為後進的榜樣。"
        },
        {
            "name": "魯道夫象徵",
            "text": "我希望各位可以避免做出不應該「效仿」的行徑──\n畢竟我是學生會長，看到妳們這樣，還是得提醒一下。"
        },
        {
            "name": "千明代表",
            "text": "明明這套制服堅韌到不會隨便跑跑就破掉。\n魯道夫妳還真是死腦筋。"
        },
        {
            "name": "天狼星象徵",
            "text": "──嗯，的確。"
        },
        {
            "name": "魯道夫象徵",
            "text": "！"
        },
        {
            "name": "天狼星象徵",
            "text": "「皇帝」陛下就是這麼不知變通。真是──太無趣了。"
        },
        {
            "name": "天狼星象徵",
            "text": "千明、丸善，妳們就別管她，盡量玩吧。\n別怕，我會把那傢伙綁在她的寶座上面。"
        },
        {
            "name": "天狼星象徵",
            "text": "那個總有一天會變得只是虛有其表的寶座。"
        },
        {
            "name": "丸善斯基",
            "text": "等一下等一下！哎呀～小狼妳真是的。\n妳跟魯道夫真的是水火不容耶。妳們從小就認識了，就不能──"
        },
        {
            "name": "天狼星象徵",
            "text": "嗯？丸善比較喜歡聊天嗎？\n我倒覺得動腳跑一跑比較有趣。"
        },
        {
            "name": "天狼星象徵",
            "text": "尤其是──把紅色「怪物」燃燒殆盡的恆星。\n實際「演出」那樣的場景，一定會很精彩。"
        },
        {
            "name": "丸善斯基",
            "text": "……討厭啦～妳就喜歡把氣氛搞得這麼緊張。"
        },
        {
            "name": "千明代表",
            "text": "哈哈！不過，天狼星，妳自己也太顧著聊天了。\n妳想跑的話就來吧？來，快點──"
        },
        {
            "name": "魯道夫象徵",
            "text": "──該停了。"
        },
        {
            "name": "魯道夫象徵",
            "text": "……快到上課時間了。我們差不多該去教室了。"
        },
        {
            "name": "魯道夫象徵",
            "text": "況且現在真的是妳該燃燒那份鬥志的時候嗎？\n若在適當的時刻、適當的地點，我隨時可以當妳的對手。"
        },
        {
            "name": "天狼星象徵",
            "text": "……哈。好啊，妳要囂張就趁現在吧。"
        },
        {
            "name": "天狼星象徵",
            "text": "我總有一天──會讓妳必須看著我奔跑的背影，魯道夫！"
        }
    ]
}