{
    "no_wrap": true,
    "title": "溫泉旅行",
    "text_block_list": [
        {
            "text": "與櫻花驀進王一起奪得無數次比賽勝利後的\n某一天──"
        },
        {
            "text": "我在訓練員室整理資料時，\n翻出了之前抽獎抽中的「溫泉旅遊券」。\n這讓我想起──"
        },
        {
            "name": "櫻花驀進王",
            "text": "等社會成為連班長都無用武之地的\n模範社會時，我們再去泡溫泉吧。"
        },
        {
            "text": "……我不太懂那句話是什麼意思，\n但旅遊券的使用期限快到了，\n所以我決定先把它拿去給櫻花驀進王。"
        },
        {
            "text": "然而──"
        },
        {
            "name": "櫻花驀進王",
            "text": "──原來如此……\n時候終於到了！！"
        },
        {
            "name": "櫻花驀進王",
            "text": "的確，我也覺得最近這社會勘稱模範！\n該怎麼說呢，就是很平靜對吧～"
        },
        {
            "name": "櫻花驀進王",
            "text": "例如上課的時候也是，有時候一回神，\n會發現課堂上從頭到尾都一片寂靜！！",
            "choice_data_list": [
                "（應該只是因為妳在打瞌睡吧？）"
            ]
        },
        {
            "name": "櫻花驀進王",
            "text": "那麼！！\n我們立刻朝溫泉驀進吧！！"
        },
        {
            "name": "櫻花驀進王",
            "text": "喔喔～～～～！\n好氣派的溫泉旅館喔！！",
            "choice_data_list": [
                "！？"
            ]
        },
        {
            "text": "在一股驀進的氣勢下，我一回神才發現，\n自己竟然什麼都沒帶就站在旅館門口了……！"
        },
        {
            "name": "櫻花驀進王",
            "text": "這才是標準的旅館！非常模範！\n有種難以言喻的班長風範呢～"
        },
        {
            "name": "櫻花驀進王",
            "text": "那麼訓練員，\n我們立刻去泡溫泉吧！"
        },
        {
            "name": "櫻花驀進王",
            "text": "不要忘記先用熱水沖過身體適應溫度，\n洗乾淨了再泡喔！"
        },
        {
            "name": "櫻花驀進王",
            "text": "要好好遵守規定！\n這才是享受樂趣的不二法門！"
        },
        {
            "text": "泡溫泉中……"
        },
        {
            "name": "櫻花驀進王",
            "text": "──呼哇～～\n泡得好舒服喔……"
        },
        {
            "name": "櫻花驀進王",
            "text": "總覺得皮膚都變光滑了！\n如何，我整個人是不是比之前更完美了呢！？",
            "choice_data_list": [
                "對啊",
                "對耶"
            ]
        },
        {
            "name": "櫻花驀進王",
            "text": "就是說嘛──！\n看來溫泉果然有讓肌膚驀進的效果。"
        },
        {
            "name": "櫻花驀進王",
            "text": "既然都變得這樣滑溜溜的，\n那速度一定也有所提升吧！？"
        },
        {
            "name": "櫻花驀進王",
            "text": "這個可得確認一下才行了……\n唔唔，溫泉……說到溫泉的速度會想到的──"
        },
        {
            "name": "櫻花驀進王",
            "text": "除了桌球沒有別的了吧！\n訓練員，我們來一決勝負吧！！",
            "choice_data_list": [
                "不是才剛洗過澡嗎！？"
            ]
        },
        {
            "name": "櫻花驀進王",
            "text": "別擔心！\n不管流幾次汗，再去洗就行了！"
        },
        {
            "name": "櫻花驀進王",
            "text": "讓我們盡情運動，再盡情泡澡吧！"
        },
        {
            "text": "我跟櫻花驀進王就如她所說，大大地活用\n旅館內的設施來盡情地暢遊了一番。\n然後──"
        },
        {
            "name": "櫻花驀進王",
            "text": "呼喔～～～～就算班長再怎麼堅不可摧……\n也實在玩到沒力了。"
        },
        {
            "name": "櫻花驀進王",
            "text": "自從立志成為班長之後，\n我好久沒有玩得這麼過癮了……"
        },
        {
            "name": "櫻花驀進王",
            "text": "因為一有旅行方面的活動，\n班長就要開始忙了！"
        },
        {
            "name": "櫻花驀進王",
            "text": "再加上我平常就以班長的身分，\n聚精會神地四處奔走……",
            "choice_data_list": [
                "（是這樣嗎？）",
                "（是這樣嗎？）"
            ]
        },
        {
            "name": "櫻花驀進王",
            "text": "今天終於能好好地放鬆一下了。"
        },
        {
            "name": "櫻花驀進王",
            "text": "話雖如此，現在這段不需要班長協助的時光\n說起來就像日蝕。"
        },
        {
            "name": "櫻花驀進王",
            "text": "而班長就是太陽，\n只會在極短的時間內被遮住。"
        },
        {
            "name": "櫻花驀進王",
            "text": "很快地，大家就會再次需要班長了。\n為此，我必須繼續當大家的榜樣！"
        },
        {
            "name": "櫻花驀進王",
            "text": "等我泡完溫泉讓肌膚滑溜溜地回去後，\n就要讓大家見識實力更上一層樓的班長囉！",
            "choice_data_list": [
                "加油！"
            ]
        },
        {
            "name": "櫻花驀進王",
            "text": "是！！"
        },
        {
            "name": "櫻花驀進王",
            "text": "……不過，那個……"
        },
        {
            "name": "櫻花驀進王",
            "text": "我也覺得要先理解班上同學吵鬧時的心情，\n才能正確地領導大家，所以……"
        },
        {
            "name": "櫻花驀進王",
            "text": "我認為現在跟訓練員多玩一下，\n或許才是模範的作法。"
        },
        {
            "name": "櫻花驀進王",
            "text": "這、這樣說沒錯……吧？",
            "choice_data_list": [
                "沒錯，盡量多玩一點吧！",
                "嗯，盡量多玩一點吧！"
            ]
        },
        {
            "name": "櫻花驀進王",
            "text": "──是♪"
        },
        {
            "text": "之後，我跟興奮喧鬧的櫻花驀進王\n一起盡情享受了在旅館的時光。"
        },
        {
            "text": "我在這段時光中，\n深刻地感受到了\n與櫻花驀進王之間無可取代的情誼……"
        }
    ]
}