{
    "no_wrap": true,
    "title": "名指導",
    "text_block_list": [
        {
            "name": "山人西風",
            "text": "呼、呼……",
            "choice_data_list": [
                "好，伸展運動做得差不多了",
                "好，伸展運動做得差不多了"
            ]
        },
        {
            "name": "山人西風",
            "text": "是的。接下來是鍛鍊軀幹的訓練吧。"
        },
        {
            "name": "山人西風",
            "text": "強度可以比昨天更高沒關係。\n我會戰勝颱風的。",
            "choice_data_list": [
                "妳今天好像特別有幹勁呢",
                "妳今天好像特別有幹勁呢"
            ]
        },
        {
            "text": "幹勁十足的山人西風，\n看起來似乎很開心。"
        },
        {
            "name": "山人西風",
            "text": "……是啊。\n因為昨天稍微吹起了青東風。"
        },
        {
            "name": "山人西風",
            "text": "第一趟……\n朝著那陣疾風……！"
        },
        {
            "name": "山人西風",
            "text": "呼！"
        },
        {
            "name": "保健室老師",
            "text": "她……是在自主訓練嗎？\n希望她不要又太過逞強了……"
        },
        {
            "name": "山人西風",
            "text": "──呼。\n現在……我離那陣疾風還很遙遠……"
        },
        {
            "name": "山人西風",
            "text": "下次一定要更靠近……"
        },
        {
            "name": "保健室老師",
            "text": "真是勤奮，但要是又太過逞強的話，\n可能又會傷到腳……要適可而止喔。"
        },
        {
            "name": "山人西風",
            "text": "……好的。我的腳……現在沒事。"
        },
        {
            "name": "保健室老師",
            "text": "那就好……哎呀？\n的確，肌肉分布得比之前\n看診的時候更均衡了呢。"
        },
        {
            "name": "保健室老師",
            "text": "剛才跑步的時候軀幹也看起來很穩定……\n是做了什麼特殊的訓練嗎？"
        },
        {
            "name": "山人西風",
            "text": "應該不算什麼特殊訓練。\n──就只是持續進行基礎鍛鍊。"
        },
        {
            "name": "山人西風",
            "text": "這樣一來，不管我乘上再狂亂的風，\n也不會被吹散……訓練員是這麼告訴我的。"
        },
        {
            "name": "保健室老師",
            "text": "哎呀……呵呵，這樣啊。\n妳遇到了很棒的訓練員呢。\n那我就放心了。"
        },
        {
            "name": "山人西風",
            "text": "……我也很感謝\n引導我們相遇的祥風。"
        },
        {
            "name": "山人西風",
            "text": "希望今後帶來恩惠的風也能繼續向我吹來──"
        },
        {
            "text": "山人西風直直地注視著我。\n於是我下定決心致力\n協助她練就足以承受疾風般奔跑的體能。"
        }
    ]
}