{
    "no_wrap": true,
    "title": "Onslaught",
    "text_block_list": [
        {
            "text": "我與克莉斯耶絲象徵一同外出後，\n在回程的路上……"
        },
        {
            "name": "克莉斯耶絲象徵",
            "text": "──到這裡就好。\n我接下來要去──mall──購物中心。",
            "choice_data_list": [
                "要去採購的話，我陪妳吧？"
            ]
        },
        {
            "name": "克莉斯耶絲象徵",
            "text": "…………我一個人就好。\n會給你──添麻煩。",
            "choice_data_list": [
                "妳想得太嚴重了"
            ]
        },
        {
            "text": "只是去採購東西，\n應該不會有什麼麻煩，\n所以我決定跟她一起去……"
        },
        {
            "text": "克莉斯耶絲象徵在甜點店訂購了餅乾，\n但是……"
        },
        {
            "name": "百貨地下商店街店員",
            "text": "……呃，大概是這樣。"
        },
        {
            "name": "克莉斯耶絲象徵",
            "text": "…………"
        },
        {
            "name": "克莉斯耶絲象徵",
            "text": "Much bigger──更大。"
        },
        {
            "name": "百貨地下商店街店員",
            "text": "那麼……是這樣嗎？"
        },
        {
            "text": "可能是在配合比手勢的克莉斯耶絲象徵，\n店員也開始比手劃腳地說明起來了。"
        },
        {
            "name": "克莉斯耶絲象徵",
            "text": "────大概這樣。",
            "choice_data_list": [
                "從剛才開始是怎麼了？",
                "從剛才開始是怎麼了？"
            ]
        },
        {
            "name": "克莉斯耶絲象徵",
            "text": "──我訂購了餅乾……\n可是搞錯了──單位。"
        },
        {
            "name": "克莉斯耶絲象徵",
            "text": "我說的是──盎司，\n──他以為是180克，太小了。",
            "choice_data_list": [
                "原來是這樣啊",
                "原來是這樣呀"
            ]
        },
        {
            "text": "她搞錯了要告訴店員的重量單位，\n於是我拜託店員等她計算好。\n然後──"
        },
        {
            "name": "克莉斯耶絲象徵",
            "text": "────五公斤！\n──我想預約五公斤份的餅乾。"
        },
        {
            "name": "百貨地下商店街店員",
            "text": "好的，五公斤是嗎？我明白了。"
        },
        {
            "name": "服飾店店員",
            "text": "…………"
        },
        {
            "name": "克莉斯耶絲象徵",
            "text": "…………"
        },
        {
            "text": "──在服飾店，\n克莉斯耶絲象徵將襯衫一件接著一件攤開又摺起、\n攤開又摺起，不斷重複這個動作。",
            "choice_data_list": [
                "這次又怎麼了？",
                "這次又怎麼了？"
            ]
        },
        {
            "name": "克莉斯耶絲象徵",
            "text": "──這襯衫的領圍──\n不可能是──三公分。"
        },
        {
            "name": "克莉斯耶絲象徵",
            "text": "──這是……日本的尺寸嗎？\n還是────"
        },
        {
            "text": "仔細一看，\n她看的好像是襯衫的尺碼。\n難不成日本跟美國的尺寸標示不同嗎……",
            "choice_data_list": [
                "總之先試穿看看吧？"
            ]
        },
        {
            "name": "克莉斯耶絲象徵",
            "text": "──原來還有這個方法。"
        },
        {
            "name": "克莉斯耶絲象徵",
            "text": "我想說──我又把單位搞錯了。\n──是我想太多了……"
        },
        {
            "name": "克莉斯耶絲象徵",
            "text": "──原來只要穿上確認一下就好……\n我去試穿了。"
        },
        {
            "name": "克莉斯耶絲象徵",
            "text": "──果然……給你添麻煩了。"
        },
        {
            "name": "克莉斯耶絲象徵",
            "text": "我……對日本──還不熟悉。\n──有很多──不了解的事。"
        },
        {
            "name": "克莉斯耶絲象徵",
            "text": "要是一開始──就清楚地──\n跟你說明這件事──就好了……"
        },
        {
            "name": "克莉斯耶絲象徵",
            "text": "────真的很抱歉。",
            "choice_data_list": [
                "下次如果有煩惱就直接告訴我吧",
                "美國的單位很難懂呢",
                "美國的單位很難懂呢"
            ]
        },
        {
            "name": "克莉斯耶絲象徵",
            "text": "────真的很抱歉。",
            "choice_data_list": [
                "下次如果有煩惱就直接告訴我吧",
                "美國的單位很難懂呢",
                "美國的單位很難懂呢"
            ]
        },
        {
            "name": "克莉斯耶絲象徵",
            "text": "──不行。我不能再給你添麻煩了。"
        },
        {
            "name": "克莉斯耶絲象徵",
            "text": "──但我很感謝──你的體貼。"
        },
        {
            "text": "她還是一樣一絲不苟……\n也正因為這樣，讓我更擔心了……"
        },
        {
            "name": "克莉斯耶絲象徵",
            "text": "對我來說──公尺跟公克──比較難懂。"
        },
        {
            "name": "克莉斯耶絲象徵",
            "text": "────國家不同，單位也不同。\n──真要說的話──會沒完沒了。"
        },
        {
            "name": "克莉斯耶絲象徵",
            "text": "──只能習慣了。"
        },
        {
            "text": "她說得沒錯。\n但是她的個性如此一絲不苟，\n讓我有點擔心她會為了習慣環境而勉強自己──"
        }
    ]
}