{
    "no_wrap": true,
    "title": "額外的自主訓練",
    "text_block_list": [
        {
            "text": "訓練結束後，當我在收拾整理時，\n聽見賽道傳來了說話聲……"
        },
        {
            "name": "菱亞馬遜",
            "text": "喔，富士！接著要不要一起來個\n「加碼」訓練呢！？"
        },
        {
            "name": "富士奇石",
            "text": "唔──我就不用了。\n好好休息也是一種訓練啊。"
        },
        {
            "name": "菱亞馬遜",
            "text": "哎呀，看妳一派輕鬆的樣子。\n這樣下次的宿舍對抗模擬賽就由我們拿下囉！"
        },
        {
            "name": "富士奇石",
            "text": "喔……妳們想贏過栗東啊。\n……挺有意思的嘛。"
        },
        {
            "name": "菱亞馬遜",
            "text": "那當然！我會利用今天大幅領先妳們的啦！！"
        },
        {
            "name": "富士奇石",
            "text": "……訓練員。\n我可以繼續練習嗎？",
            "choice_data_list": [
                "可以啊！",
                "先養精蓄銳吧！"
            ]
        },
        {
            "name": "富士奇石",
            "text": "既然有你的認可，那就不用客氣了呢……！"
        },
        {
            "name": "富士奇石",
            "text": "好啦，菱亞！來練吧！"
        },
        {
            "name": "菱亞馬遜",
            "text": "嘿嘿……那傢伙有時候會變得\n比我還激動呢……！"
        },
        {
            "name": "富士奇石",
            "text": "……嗯，說得也是。\n我還是照原先的安排休息吧。"
        },
        {
            "name": "菱亞馬遜",
            "text": "怎麼，妳不練嗎！？"
        },
        {
            "name": "富士奇石",
            "text": "我要照顧好身體，以策萬全。\n當然，這都是為了在模擬賽獲勝！"
        }
    ]
}