{
    "no_wrap": true,
    "title": "迎向短途跑者S",
    "text_block_list": [
        {
            "name": "喜嘉奇蹟",
            "text": "…………"
        },
        {
            "name": "第一紅寶",
            "text": "……奇蹟。"
        },
        {
            "name": "喜嘉奇蹟",
            "text": "……"
        },
        {
            "name": "第一紅寶",
            "text": "奇蹟。"
        },
        {
            "name": "喜嘉奇蹟",
            "text": "……！"
        },
        {
            "name": "喜嘉奇蹟",
            "text": "抱歉，什麼事……？"
        },
        {
            "name": "第一紅寶",
            "text": "沒什麼，差不多該出門了，\n所以我想先跟妳打個招呼。"
        },
        {
            "name": "喜嘉奇蹟",
            "text": "啊，這樣啊。\n時間到了啊……"
        },
        {
            "name": "第一紅寶",
            "text": "……"
        },
        {
            "name": "喜嘉奇蹟",
            "text": "抱歉，我沒事。\n只是在想些事情。"
        },
        {
            "name": "喜嘉奇蹟",
            "text": "來一場……\n令彼此都沒有遺憾的比賽吧。"
        },
        {
            "name": "喜嘉奇蹟",
            "text": "那就──中山賽場見了。"
        },
        {
            "name": "第一紅寶",
            "text": "……好的。"
        },
        {
            "text": "今年的「短途跑者S」──\n也有許多備受注目的賽馬娘參賽。"
        },
        {
            "name": "觀眾A",
            "text": "喔，山人西風！\n好期待看到她今天能發揮多少實力喔。",
            "color_text_info_list": [
                "山人西風"
            ]
        },
        {
            "text": "（山人西風……散發著神秘氣息的\n經典級賽馬娘。她還沒贏過主要競賽，\n但還是像隨興的風一般，來挑戰GⅠ競賽。）"
        },
        {
            "name": "觀眾B",
            "text": "西風也值得注目沒錯啦，\n但說到現在經典級，\n果然還是……啊，來了！",
            "color_text_info_list": [
                "西風"
            ]
        },
        {
            "name": "記者A",
            "text": "喂，千萬要拍到啊！\n──那兩人要登場啦！"
        },
        {
            "name": "觀眾們",
            "text": "第一紅寶！\n喜嘉奇蹟～～～～！！"
        },
        {
            "name": "觀眾B",
            "text": "我還是看好氣勢正旺的奇蹟啦！\n今天她搞不好也能跑出新紀錄喔！？"
        },
        {
            "name": "觀眾A",
            "text": "紅寶在「安田紀念」的表現……\n讓我印象深刻。妳、妳要加油！"
        },
        {
            "name": "記者A",
            "text": "接連刷新紀錄並獲勝的喜嘉奇蹟、\n「華麗一族」的第一紅寶……"
        },
        {
            "name": "記者A",
            "text": "今天即將揭曉\n誰才是最快的賽馬娘……！"
        },
        {
            "name": "喜嘉奇蹟",
            "text": "各位，\n謝謝你們到場加油。"
        },
        {
            "name": "喜嘉奇蹟",
            "text": "今天……我一定會展現奇蹟。"
        },
        {
            "name": "喜嘉奇蹟",
            "text": "──獻上一切也在所不惜。"
        },
        {
            "name": "觀眾C",
            "text": "……怎麼覺得奇蹟她……氣勢好驚人？\n甚至……好像有點恐怖。",
            "choice_data_list": [
                "（喜嘉奇蹟……）"
            ]
        },
        {
            "text": "如同第一紅寶所說，\n喜嘉奇蹟顯然經過一番嚴格鍛鍊，\n將自己磨練得相當完美。"
        },
        {
            "text": "她雖然和平時一樣溫和，\n但是氣息中散發著駭人的氣魄。"
        },
        {
            "name": "第一紅寶",
            "text": "……"
        },
        {
            "name": "第一紅寶",
            "text": "（我將會展現──）"
        },
        {
            "name": "喜嘉奇蹟",
            "text": "「呼…………！！」"
        },
        {
            "name": "第一紅寶",
            "text": "（我也會追上妳的速度，\n到達妳的境地。）"
        },
        {
            "name": "第一紅寶",
            "text": "（──然後，我會繼續往前方而去……\n這樣的話，妳也會看向未來吧。）"
        },
        {
            "name": "年幼的紅寶",
            "text": "（我要在比賽留下輝煌功績，成為家族的驕傲。\n然後……我要被掛在正中間那幅最大的\n母親的畫像旁邊……！）"
        },
        {
            "name": "第一紅寶",
            "text": "（──就像是受過大家的光芒引導的我。）"
        },
        {
            "name": "喜嘉奇蹟",
            "text": "…………一定要贏。"
        },
        {
            "name": "喜嘉奇蹟",
            "text": "要跑得比誰都快……\n今天……一定要跑贏大家──"
        },
        {
            "name": "第一紅寶",
            "text": "奇蹟。"
        },
        {
            "name": "喜嘉奇蹟",
            "text": "紅寶……"
        },
        {
            "name": "喜嘉奇蹟",
            "text": "……今天請多指教了。\n妳當然不需要客氣。"
        },
        {
            "name": "喜嘉奇蹟",
            "text": "為了各自心中無法退讓的事物……\n一決高下吧──"
        },
        {
            "name": "第一紅寶",
            "text": "──獻上一切也在所不惜。"
        },
        {
            "name": "喜嘉奇蹟",
            "text": "！"
        },
        {
            "name": "第一紅寶",
            "text": "我絕對不能將最快的榮耀\n讓給現在的妳。"
        },
        {
            "name": "第一紅寶",
            "text": "改寫妳被賦予的「事物」，\n正是我的……"
        },
        {
            "name": "喜嘉奇蹟",
            "text": "紅寶……？"
        },
        {
            "name": "第一紅寶",
            "text": "…………"
        },
        {
            "name": "第一紅寶",
            "text": "我要以領先者之姿，\n帶妳前往更高峰。"
        },
        {
            "name": "第一紅寶",
            "text": "──敬請見證「華麗一族」那\n打動人心的跑姿。"
        },
        {
            "name": "第一紅寶",
            "text": "──我一定會贏得今天這場比賽。"
        },
        {
            "text": "出發前往比賽前……\n第一紅寶突然如此宣言。"
        },
        {
            "text": "肩負「華麗一族」之名的她\n至今都只放眼勝利。\n那麼，現在特地大聲宣言的意義是……",
            "choice_data_list": [
                "（……先靜靜聽她說完吧）"
            ]
        },
        {
            "text": "我想她一定……\n正在藉由實際說出口來整理思緒，\n釐清自己傾注在這場比賽上的意念。"
        },
        {
            "name": "第一紅寶",
            "text": "我要獲得不容質疑、震撼一切的勝利。\n……使得那前方得以看見光芒。"
        },
        {
            "name": "第一紅寶",
            "text": "我要綻放\n令對手不禁渴望超越我的光芒──"
        },
        {
            "name": "第一紅寶",
            "text": "我要展現最耀眼的光芒，\n以指引出應該走向的未來。"
        },
        {
            "name": "第一紅寶",
            "text": "這就是我的……\n不對，是「華麗一族」的使命。"
        },
        {
            "name": "第一紅寶",
            "text": "……直到現在，\n我才終於打從心底理解這點。"
        },
        {
            "name": "第一紅寶",
            "text": "沒錯，邁向未來。\n我們──得用自己的雙腳前進。"
        },
        {
            "text": "看樣子，她的意志已經堅定下來。\n那麼，我該對她說的就只有一句話──",
            "choice_data_list": [
                "去吧！"
            ]
        },
        {
            "name": "第一紅寶",
            "text": "好的。"
        },
        {
            "name": "第一紅寶",
            "text": "──我這就去達成使命。"
        }
    ]
}