{
    "no_wrap": true,
    "title": "迎向一哩CS",
    "text_block_list": [
        {
            "name": "獨白",
            "text": "「一哩CS」。大樹快車很早以前，\n就曾宣告會挑戰這場競賽──"
        },
        {
            "name": "大樹快車",
            "text": "Yes, victory！！"
        },
        {
            "name": "獨白",
            "text": "她在之前的GⅡ也漂亮地拿下勝利，\n勢如破竹地前來參賽。\n不過，我們也──"
        },
        {
            "name": "採珠",
            "text": "能做的努力全都done……\n訓練員，我們已經盡全力了。"
        },
        {
            "name": "採珠",
            "text": "走吧。終於要在閃耀系列賽，\n和大樹進行第一次對決了！",
            "choice_data_list": [
                "是啊，儘管接受她的挑戰吧！",
                "嗯，儘管接受她的挑戰吧！"
            ]
        },
        {
            "name": "採珠",
            "text": "接受挑戰……說得也是，就資歷而言，\n我在她之上。不過──"
        },
        {
            "name": "採珠",
            "text": "我完全……沒有這種感覺。\n因為我比誰都清楚她的實力。"
        },
        {
            "name": "獨白",
            "text": "大樹快車一定滿心想要贏下這場比賽。\n我原本是這麼想的……"
        },
        {
            "name": "大樹快車",
            "text": "Oh……採珠……\n我都聽說了……"
        },
        {
            "name": "大樹快車",
            "text": "妳喉嚨的狀況a little不太好。\n妳還好嗎？"
        },
        {
            "name": "大樹快車",
            "text": "難得的機會，\n我真想跟狀態更好的妳一起跑……"
        },
        {
            "name": "採珠",
            "text": "哎呀，大樹，妳在擔心我嗎？\n謝謝妳，不過……"
        },
        {
            "name": "採珠",
            "text": "不用擔心。\n不如說，正好相反。"
        },
        {
            "name": "採珠",
            "text": "能在這樣的狀態下與妳對決。\n讓我開心得不得了。"
        },
        {
            "name": "大樹快車",
            "text": "……What's？\n妳明明會喘不過氣……Why？"
        },
        {
            "name": "獨白",
            "text": "採珠的眼神，\n正散發出前所未有的燦爛光芒。"
        },
        {
            "name": "採珠",
            "text": "每個人都想要safety地生活。\n在自己力所能及的範圍內求安穩。"
        },
        {
            "name": "採珠",
            "text": "可是我卻不被允許這麼做。\n因為有個巨大的hard luck落在我身上。"
        },
        {
            "name": "採珠",
            "text": "但也正因為如此，我才開創出了新的可能性！"
        },
        {
            "name": "採珠",
            "text": "採用新的跑法！新的tactics！\n並抱持著新的決心奔跑！"
        },
        {
            "name": "採珠",
            "text": "這才是truth！\n才是真正的「奔跑」。"
        },
        {
            "name": "大樹快車",
            "text": "真正的……"
        },
        {
            "name": "採珠",
            "text": "沒錯，光是隨波逐流，自然地生活，\n並不能算是活著。"
        },
        {
            "name": "採珠",
            "text": "沒錯，有限才是無限！Limited才是\nunlimited！而疾病才是助力！"
        },
        {
            "name": "採珠",
            "text": "我按照自己的想像，磨練並創造出\n新的自己。大樹，這都是為了與妳對決。"
        },
        {
            "name": "採珠",
            "text": "這樣的我若能超越妳，一定會比自然而然地\n贏過妳更加美好，妳不這麼覺得嗎？"
        },
        {
            "name": "大樹快車",
            "text": "採珠……我不太懂……妳的意思。\n不過……"
        },
        {
            "name": "大樹快車",
            "text": "我明白了一件事！\n那就是妳現在狀態絕佳！"
        },
        {
            "name": "採珠",
            "text": "是啊，妳說得沒錯。\n所以儘管放膽過來吧。"
        },
        {
            "name": "採珠",
            "text": "另外……\n我同時打算在這場對決賭上重要的東西。"
        },
        {
            "name": "採珠",
            "text": "如果，我完全無法與妳抗衡，\n就這樣埋沒在跑者群中──"
        },
        {
            "name": "採珠",
            "text": "我就the end……\n表示我沒有能力挑戰世界。沒錯──"
        },
        {
            "name": "採珠",
            "text": "──這是一場test。\n測試嶄新的我。"
        },
        {
            "name": "獨白",
            "text": "採珠以有些悲傷的眼神看向我。\n身為訓練員，\n我必須冷靜地評斷她今天的表現。"
        },
        {
            "name": "採珠",
            "text": "話雖如此，\n我當然完全沒打算在此surrender！"
        },
        {
            "name": "採珠",
            "text": "來吧，大樹！\n在這個stardom舞台上！\n盡情享受彼此的可能性吧♪"
        }
    ]
}