{
    "no_wrap": true,
    "title": "迎向天皇賞（秋）",
    "text_block_list": [
        {
            "name": "谷水琴蕾",
            "text": "我將降臨於「天皇賞（秋）」。\n去年是復活之人，今年則是破壞神！"
        },
        {
            "name": "谷水琴蕾",
            "text": "吾的考驗是連續兩年的決鬥！\n命運女神雖然殘暴，但是絕對不會讓人感到無趣。"
        },
        {
            "name": "谷水琴蕾",
            "text": "沒錯……在創世前我一定便渴望著──\n這個剎那。"
        },
        {
            "name": "谷水琴蕾",
            "text": "來實現永恆之前的約定吧。\n「克莉斯耶絲象徵」，跟我一決勝負……！",
            "color_text_info_list": [
                "克莉斯耶絲象徵"
            ]
        }
    ]
}