{
    "no_wrap": true,
    "title": "舞蹈練習",
    "text_block_list": [
        {
            "name": "獨白",
            "text": "我跟谷水琴蕾出門採買，\n回程路上突然下起雨來。",
            "choice_data_list": [
                "我沒有帶傘……！"
            ]
        },
        {
            "name": "獨白",
            "text": "於是我們急忙跑到看起來可以躲雨的屋簷下，\n但是──"
        },
        {
            "name": "谷水琴蕾",
            "text": "喂，你為什麼躲到屋簷下？",
            "choice_data_list": [
                "咦！？妳、妳會淋溼的！",
                "咦！？妳、妳會淋溼的！"
            ]
        },
        {
            "name": "獨白",
            "text": "谷水琴蕾不知道什麼時候走出屋簷，\n一邊淋著雨，\n一邊若無其事地說話。"
        },
        {
            "name": "谷水琴蕾",
            "text": "這種小事──微不足道！！\n只要有凌駕於冰冷雨水之上的熱情就沒問題！！"
        },
        {
            "name": "谷水琴蕾",
            "text": "你聽見雨聲的旋律了嗎？\n遺忘喧囂的商店街……"
        },
        {
            "name": "谷水琴蕾",
            "text": "現在，這個瞬間──\n這裡成為了舞台！！"
        },
        {
            "name": "谷水琴蕾",
            "text": "來吧──享受這場雨。",
            "choice_data_list": [
                "哇──"
            ]
        },
        {
            "name": "獨白",
            "text": "她拉著我的手，把我帶到雨中。\n我的衣服一下子就溼掉了。"
        },
        {
            "name": "谷水琴蕾",
            "text": "別被框架限制住，用熱情來配合！"
        },
        {
            "name": "獨白",
            "text": "我待在雨裡，\n費了一番功夫才跟上谷水琴蕾的動作，\n結果──"
        },
        {
            "name": "獨白",
            "text": "我受到她的影響，動作漸漸變得大膽。\n踩了許多次水窪後，我的腳邊泥濘不堪。\n但是……"
        },
        {
            "name": "獨白",
            "text": "我沒有感覺到溼掉的衣服重量，\n也沒有感受到雨水的冰冷。\n只專注於這個瞬間──"
        },
        {
            "name": "谷水琴蕾",
            "text": "──很有趣吧？"
        },
        {
            "name": "獨白",
            "text": "……我聽見掌聲才回過神來。\n不知不覺間，雨已經停了。"
        },
        {
            "name": "商店街的人們",
            "text": "──好耶！你們跳得不錯啊！\n──這支舞棒極了。"
        },
        {
            "name": "谷水琴蕾",
            "text": "只有充分運用舞台的人，\n才能享受到女神哈索爾的祝福。"
        },
        {
            "name": "谷水琴蕾",
            "text": "你獲得了新的知識樹果呢。\n民眾們，謝謝你們。然後──"
        },
        {
            "name": "谷水琴蕾",
            "text": "為自己有幸看見吾等泡沫般的舞蹈\n感到幸運吧！！"
        },
        {
            "name": "獨白",
            "text": "掌聲綿延不絕，\n谷水琴蕾心情非常好，只是──",
            "choice_data_list": [
                "這對心臟不太好，希望她能適可而止……",
                "雨停了，真可惜呢",
                "雨停了，真可惜呢"
            ]
        },
        {
            "name": "獨白",
            "text": "掌聲綿延不絕，\n谷水琴蕾心情非常好，只是──",
            "choice_data_list": [
                "這對心臟不太好，希望她能適可而止……",
                "雨停了，真可惜呢",
                "雨停了，真可惜呢"
            ]
        },
        {
            "name": "獨白",
            "text": "要是之後也要突然跳舞，\n我有幾顆心臟都不夠用！\n語畢，我將毛巾遞給她──"
        },
        {
            "name": "谷水琴蕾",
            "text": "什麼嘛，\n我的舞伴清醒得還真快。"
        },
        {
            "name": "谷水琴蕾",
            "text": "不過偶爾也要像這樣放縱一下。\n如果我們無法樂在其中，\n觀眾也沒辦法看得開心。"
        },
        {
            "name": "谷水琴蕾",
            "text": "呵呵……\n這跟華麗的勝利之宴有異曲同工之妙！"
        },
        {
            "name": "獨白",
            "text": "她說得沒錯，在雨中跳舞很開心……\n更重要的是，\n谷水琴蕾充滿活力的模樣讓我心情很好。"
        },
        {
            "name": "獨白",
            "text": "透過讓自己樂在其中，取悅觀眾……\n我似乎稍微明白了她對演唱會的看法。"
        },
        {
            "name": "獨白",
            "text": "因為有趣，才會覺得轉瞬即逝。\n真希望這段時間可以持續下去。\n語畢，我將毛巾遞給她──"
        },
        {
            "name": "谷水琴蕾",
            "text": "是啊，我也這麼想──\n這段時間真是令人愉悅。"
        },
        {
            "name": "谷水琴蕾",
            "text": "不過，正因為時間一轉眼便飛逝而去，\n看起來才會特別鮮明。"
        },
        {
            "name": "谷水琴蕾",
            "text": "華麗的勝利之宴也是這個道理……\n觀眾會被剎那間的光芒深深吸引。"
        },
        {
            "name": "獨白",
            "text": "在這個下雨天裡，\n我稍微明白了她對演唱會的看法。"
        }
    ]
}