{
    "no_wrap": true,
    "title": "有馬紀念結束後．英雄的逆襲",
    "text_block_list": [
        {
            "text": "新宇宙在「日本盃」獲得優勝。\n不過在「有馬紀念」……"
        },
        {
            "name": "播報員",
            "text": "荒漠英雄！是荒漠英雄！"
        },
        {
            "name": "播報員",
            "text": "英雄在此崛起！\n她現在高高地舉起了勝利之劍！！"
        },
        {
            "name": "荒漠英雄",
            "text": "謝謝大家──！！"
        },
        {
            "text": "荒漠英雄扳回了一城。\n今年秋冬是「平分秋色」。"
        },
        {
            "name": "新宇宙",
            "text": "荒漠英雄，新宇宙要傳達「祝賀」喔，\n還有……"
        },
        {
            "name": "新宇宙",
            "text": "妳變強了呢。"
        },
        {
            "name": "荒漠英雄",
            "text": "宇宙，謝謝妳！"
        },
        {
            "name": "荒漠英雄",
            "text": "那個……\n妳說「變強」是指跟「日本盃」相比嗎？"
        },
        {
            "name": "新宇宙",
            "text": "──否定。\n「變強」獲得認可是……"
        },
        {
            "name": "新宇宙",
            "text": "跟「ANOI」的「有馬紀念」相比。\n妳描繪的上升軌道\n比那場比賽更高。"
        },
        {
            "name": "新宇宙",
            "text": "荒漠英雄，\n〔我〕們正在追逐。"
        },
        {
            "name": "新宇宙",
            "text": "──大氣中的「幽靈之驅」。"
        },
        {
            "name": "荒漠英雄",
            "text": "大氣中的……幽靈……\n雖然有點困難，但是大概可以理解。"
        },
        {
            "name": "荒漠英雄",
            "text": "超越存在於某處的自己，然後──"
        },
        {
            "name": "荒漠英雄",
            "text": "總有一天要追趕上理想的自己！\n對吧？"
        },
        {
            "name": "新宇宙",
            "text": "──嗯。"
        },
        {
            "text": "乍看之下都是勝利，\n但是荒漠英雄變得更加堅強了。"
        },
        {
            "text": "她們接下來也會繼續奔馳。\n以超越其他宇宙的「幽靈之驅」為目標，\n永無止盡地跑下去。"
        }
    ]
}