{
    "no_wrap": true,
    "title": "舞蹈練習",
    "text_block_list": [
        {
            "name": "東商變革",
            "text": "不要！我不要跳舞！\n要跳你自己一個人跳！"
        },
        {
            "name": "獨白",
            "text": "我帶東商變革來到舞蹈室\n接受舞蹈課的課後輔導，但是……\n這樣下去只會白白浪費時間。",
            "choice_data_list": [
                "妳不跳就沒意義了……",
                "妳不跳就沒意義了……"
            ]
        },
        {
            "name": "東商變革",
            "text": "我才不管呢！\n我要累積魔法能量，很忙的！"
        },
        {
            "name": "？？？",
            "text": "哎呀，這樣跳舞就是最好的方法！\n我也正好要透過跳舞累積能量呢！"
        },
        {
            "name": "川上公主",
            "text": "沒錯──就是用Prinfight第三季的片尾曲，\n「公主☆派對」！",
            "choice_data_list": [
                "「公主☆派對」？"
            ]
        },
        {
            "name": "川上公主",
            "text": "與其用說的，還是直接讓你們看比較快！\n我要開始囉──"
        },
        {
            "name": "川上公主",
            "text": "喝啊啊啊啊！\n哈、嘿、呀────！！"
        },
        {
            "name": "東商變革",
            "text": "咦！？\n川上的體內湧出了能量……！！"
        },
        {
            "name": "獨白",
            "text": "激烈的舞蹈讓她的身體開始散發熱氣，\n看起來就像是魔法的能量……！"
        },
        {
            "name": "川上公主",
            "text": "呼……怎麼樣？\n有看見強大的「公主☆能量」了嗎？"
        },
        {
            "name": "東商變革",
            "text": "看見了！快點教我舞步！\n我也要累積很厲害的能量！",
            "choice_data_list": [
                "（好吧，反正也能當成是舞蹈練習吧！）",
                "（好吧，反正也能當成是舞蹈練習呢！）"
            ]
        },
        {
            "name": "東商變革",
            "text": "Yes♪全力將所有敵人打得落花流水♪\n戰鬥公主閃亮登場囉♪"
        },
        {
            "name": "川上公主",
            "text": "所有人集結在后冠之下♪"
        },
        {
            "name": "兩人",
            "text": "活力十足的公主♪耶～！"
        },
        {
            "name": "東商變革",
            "text": "呼、呼……感覺身體熱起來了！\n這該不會就是……！？"
        },
        {
            "name": "川上公主",
            "text": "沒錯！妳成功累積能量了！\n表情也變得完全不一樣了喔！"
        },
        {
            "name": "東商變革",
            "text": "因為感覺好興奮！\n還有其他有趣的舞蹈嗎？快點教我！",
            "choice_data_list": [
                "不用休息沒關係嗎？",
                "還有其他舞蹈能累積更多能量喔"
            ]
        },
        {
            "name": "東商變革",
            "text": "對耶！這種時候就要──"
        },
        {
            "name": "東商變革",
            "text": "披薩草．復原術！\n來喝能夠消除疲勞的魔法水吧！"
        },
        {
            "name": "川上公主",
            "text": "充電完畢！\n準備火力全開，盡情跳舞囉～～！！"
        },
        {
            "name": "獨白",
            "text": "不知道是不是東商變革非常喜歡這種舞蹈，\n她跳得越來越起勁！"
        },
        {
            "name": "東商變革",
            "text": "你知道喔！？使魔，你真有一套！\n那是什麼樣的舞蹈啊？",
            "choice_data_list": [
                "就是演唱會時跳的舞……"
            ]
        },
        {
            "name": "川上公主",
            "text": "演唱會的確就是能量的集合體！\n感覺可以更進一步地提升力量！"
        },
        {
            "name": "東商變革",
            "text": "聽你們這麼說有道理耶……！\n……使魔！快點放曲子！"
        },
        {
            "name": "獨白",
            "text": "之後東商變革認真練舞，\n一直練到很晚！"
        }
    ]
}