{
    "no_wrap": true,
    "title": "隱藏的過去",
    "text_block_list": [
        {
            "text": "瞞著樫本代理開始進行自主訓練的\n隊伍＜急速＞。"
        },
        {
            "name": "大樹快車",
            "text": "我感覺隊伍＜急速＞她們的\n氣氛變得不一樣了！"
        },
        {
            "name": "春烏菈菈",
            "text": "昨天我在宿舍的餐廳，\n看見她們一起邊討論很難懂的話題邊吃飯喔！"
        },
        {
            "name": "春烏菈菈",
            "text": "她們本來都是自己一個人吃飯，\n讓我嚇了一跳！"
        },
        {
            "text": "然後某一天，我和大樹快車結束訓練後，\n一起在回程的途中──"
        },
        {
            "text": "撞見了隊伍＜急速＞的成員們，\n正受到叱責的場面。"
        },
        {
            "name": "樫本理子",
            "text": "妳們難道以為我不會發現嗎……！\n未免太小看我了。"
        },
        {
            "name": "小巧圓繭",
            "text": "不是的！我們只是……"
        },
        {
            "name": "小巧圓繭",
            "text": "……在練習賽的時候，\n和對手相比完全沒有成長，所以才……"
        },
        {
            "name": "樫本理子",
            "text": "不需要在意那種事情！"
        },
        {
            "name": "小巧圓繭",
            "text": "但是妳為我們每個人，\n都分別制定了詳盡的計畫……！"
        },
        {
            "name": "小巧圓繭",
            "text": "是我們自己表現得不夠好。\n所以，必須靠自己更進一步地成長……！"
        },
        {
            "name": "樫本理子",
            "text": "為什麼要想那種多餘的事！"
        },
        {
            "name": "樫本理子",
            "text": "妳們只要照我的指示去跑就夠了！\n這麼說都是為了妳們好！"
        },
        {
            "name": "樫本理子",
            "text": "……我的情緒有點太激動了。\n今天就先到此為止，解散吧。"
        },
        {
            "name": "小巧圓繭",
            "text": "…………抱歉。\n都是我的錯。"
        },
        {
            "text": "隊伍＜急速＞意氣消沉，不發一語。\n當我屏住呼吸看著眼前所發生的事時──"
        },
        {
            "name": "大樹快車",
            "text": "Hey！What！？這太奇怪了！"
        },
        {
            "name": "隊伍＜急速＞",
            "text": "……！"
        },
        {
            "name": "大樹快車",
            "text": "大家並沒有錯！\n希望自己成長的心情是理所當然的！"
        },
        {
            "name": "大樹快車",
            "text": "樫本代理沒有好好愛惜隊友……！"
        },
        {
            "name": "小巧圓繭",
            "text": "不對。"
        },
        {
            "name": "大樹快車",
            "text": "！"
        },
        {
            "name": "小巧圓繭",
            "text": "樫本訓練員非常認真地為我們著想。\n也很愛惜我們。"
        },
        {
            "name": "微苦糖漬",
            "text": "無論是飲食管理還是訓練項目，\n都非常用心為我們的身體著想。"
        },
        {
            "text": "像是呼應她般，\n周圍的隊伍成員也頻頻點頭。",
            "choice_data_list": [
                "既然如此為什麼……"
            ]
        },
        {
            "text": "就算是用心著想，做法也太過強硬。\n完全不願接受其他方式。"
        },
        {
            "text": "而且秋川理事長對樫本代理的作法靜觀其變，\n仔細想想也有很多奇怪的地方。"
        },
        {
            "text": "這時我突然回想起，\n之前手綱小姐曾經說過的話。"
        },
        {
            "name": "駿川手綱",
            "text": "畢竟理事長非常了解學園的大小事情，\n或許她的著眼點和我們不同也說不定……"
        },
        {
            "text": "秋川理事長或許知道些什麼。\n於是我和隊伍成員與隊伍＜急速＞一起，\n前去秋川理事長面前。"
        },
        {
            "text": "話題進展得很快。"
        },
        {
            "name": "秋川理事長",
            "text": "原來如此，了解！\n各位有權利知道！"
        },
        {
            "name": "秋川理事長",
            "text": "我說給你們聽吧！為何！\n她對賽馬娘們會如此過度管理！\n其背後原因！"
        },
        {
            "text": "根據秋川理事長的描述──過去的樫本代理，\n原本是個尊重賽馬娘自由意志的訓練員。"
        },
        {
            "text": "與專任賽馬娘建立了深厚的\n信賴關係，並在閃耀系列賽\n留下了優秀的成績。"
        },
        {
            "text": "就在此時，舉辦了「青春盃」，\n開始了隊伍對抗賽。"
        },
        {
            "name": "專任賽馬娘",
            "text": "用隊伍的方式對戰，會是什麼樣子呢！\n大家會一起做訓練吧！？"
        },
        {
            "name": "專任賽馬娘",
            "text": "我……那個……到目前為止\n都沒有什麼朋友……所以我非常期待！"
        },
        {
            "name": "樫本理子",
            "text": "是啊。\n我也很期待妳的成長。"
        },
        {
            "text": "可是……\n集結到的隊伍成員實力在平均以下。\n與其專任賽馬娘的實力有很明顯的差距。"
        },
        {
            "name": "樫本理子",
            "text": "要追加隊伍的自主訓練，是嗎？\n但是──"
        },
        {
            "name": "專任賽馬娘",
            "text": "我也很清楚，\n現在是閃耀系列賽的緊要關頭！"
        },
        {
            "name": "專任賽馬娘",
            "text": "但是，有很多地方是我可以教她們的……"
        },
        {
            "name": "專任賽馬娘",
            "text": "如果是我能辦到的事，我想幫大家的忙！\n拜託了！"
        },
        {
            "text": "隊伍成員們努力地想填補實力差距，\n那位專任賽馬娘也為了她們盡心盡力。"
        },
        {
            "name": "專任賽馬娘",
            "text": "…………"
        },
        {
            "name": "樫本理子",
            "text": "……妳似乎累積了不少疲勞。"
        },
        {
            "name": "樫本理子",
            "text": "目標的經典級主要競賽也快到了。\n下次的「青春盃」還是休息吧？",
            "color_text_info_list": [
                "經典級",
                "主要競賽"
            ]
        },
        {
            "name": "專任賽馬娘",
            "text": "……但是我不參賽的話，\n說不定隊伍的排名會掉下來。"
        },
        {
            "name": "專任賽馬娘",
            "text": "好不容易提升起來的訓練強度，\n不能在這時停下。現在是必須努力的時候。"
        },
        {
            "name": "樫本理子",
            "text": "……\n我明白了，我會尊重妳的決定。"
        },
        {
            "text": "此時要是輕率地潑冷水，\n可能會破壞她們建立起來的向心力。"
        },
        {
            "text": "樫本代理決定相信專任賽馬娘和專任隊伍。"
        },
        {
            "text": "可是，就在某天──"
        },
        {
            "name": "播報員",
            "text": "──接近第三彎道時跌倒了！她跌倒了！\n不要緊嗎！？"
        },
        {
            "text": "（救護車前來……）"
        },
        {
            "name": "醫生",
            "text": "原因是疲勞性骨折導致姿勢失去重心。\n看來她相當勉強自己。"
        },
        {
            "name": "醫生",
            "text": "正常生活是沒什麼問題，\n但要作為賽馬娘參賽恐怕已經──"
        },
        {
            "text": "那位專任賽馬娘因為這場事故而退出第一線。\n之後也從特雷森學園輟學了。"
        },
        {
            "name": "樫本理子",
            "text": "如果我有好好看住那孩子的話……！"
        },
        {
            "name": "秋川理事長",
            "text": "於是她從那刻起！便對因放任而引起的\n感情失控感到畏懼──"
        },
        {
            "name": "秋川理事長",
            "text": "並抱持著唯有透過管理，\n才能徹底保護賽馬娘的堅定信念！"
        },
        {
            "name": "小巧圓繭",
            "text": "…………可、可是！"
        },
        {
            "name": "小巧圓繭",
            "text": "因為樫本訓練員的管理教育網領相當完美，\n所以才使我們獲得了成長！"
        },
        {
            "name": "秋川理事長",
            "text": "嗯！確實她的本事是首屈一指！\n對賽馬娘而言也是不可或缺！"
        },
        {
            "name": "秋川理事長",
            "text": "正因如此，我目前還在摸索！\n要用何方法讓她醒悟！"
        },
        {
            "text": "樫本代理的過去及秋川理事長的行動之謎……\n雖然全部解開了，但是另一方面──"
        },
        {
            "text": "未曾想像的樫本代理的過去，\n使在場的每個人都說不出話來……"
        }
    ]
}