{
    "no_wrap": true,
    "title": "舞蹈練習",
    "text_block_list": [
        {
            "name": "獨白",
            "text": "我正在陪醒目飛鷹練舞……"
        },
        {
            "name": "醒目飛鷹",
            "text": "一、二、三……\n噠、噠、噠……"
        },
        {
            "name": "醒目飛鷹",
            "text": "──最後一步！\n收尾的轉身！"
        },
        {
            "name": "獨白",
            "text": "（──咻！）",
            "choice_data_list": [
                "真是完美啊！",
                "真是完美呢！"
            ]
        },
        {
            "name": "醒目飛鷹",
            "text": "嘿嘿♪對賽馬娘偶像來說，\n成為舞步專家可是很基本的喔☆"
        },
        {
            "name": "醒目飛鷹",
            "text": "不過，飛飛的目標是賽馬娘偶像界的\n頂點──頂尖賽馬娘偶像！"
        },
        {
            "name": "醒目飛鷹",
            "text": "所以飛飛的舞蹈練習呢，\n接下來才是重頭戲……！",
            "choice_data_list": [
                "什麼意思？"
            ]
        },
        {
            "name": "醒目飛鷹",
            "text": "你想想看，每首歌曲跟每個站位的舞步\n不都是固定的嗎？"
        },
        {
            "name": "醒目飛鷹",
            "text": "但是頂尖賽馬娘偶像的舞蹈\n需要獨一無二的魅力──"
        },
        {
            "name": "醒目飛鷹",
            "text": "除了跟其他人一樣的舞步之外，\n也得展現飛飛專屬的魅力才行！",
            "choice_data_list": [
                "原來如此……"
            ]
        },
        {
            "name": "醒目飛鷹",
            "text": "所以飛飛想創造一個能讓大家\n怦然心動的特別姿勢……"
        },
        {
            "name": "醒目飛鷹",
            "text": "訓練員，也跟我說說你的想法吧！\n怎麼樣才能展現獨一無二的魅力呢？",
            "choice_data_list": [
                "只能腳踏實地練習",
                "用特別的方式宣傳自己吧"
            ]
        },
        {
            "name": "醒目飛鷹",
            "text": "啊……！\n只能腳踏實地練習……！"
        },
        {
            "name": "醒目飛鷹",
            "text": "難道說，用一樣的動作也能自然吸引\n大家的目光，才是真正的可愛嗎！？",
            "choice_data_list": [
                "沒錯！"
            ]
        },
        {
            "name": "醒目飛鷹",
            "text": "飛飛還以為……要跟大家做不一樣的事，\n才能展現獨一無二的魅力。"
        },
        {
            "name": "醒目飛鷹",
            "text": "沒想到還有這種思考方式啊……！\n謝謝你！訓練員☆"
        },
        {
            "name": "醒目飛鷹",
            "text": "好──！我會比任何人都更努力練習，\n一定要成為頂尖賽馬娘偶像──♪"
        },
        {
            "name": "獨白",
            "text": "後來，醒目飛鷹更加投入練習了。"
        },
        {
            "name": "醒目飛鷹",
            "text": "嗯嗯！\n果然是那樣沒錯♪"
        },
        {
            "name": "醒目飛鷹",
            "text": "為了把獨一無二的魅力\n展現給來看表演的粉絲──"
        },
        {
            "name": "醒目飛鷹",
            "text": "我必須盡全力磨練\n特別出眾的宣傳方式才行！"
        },
        {
            "name": "醒目飛鷹",
            "text": "所以……怎麼樣？\n飛飛可愛嗎？",
            "choice_data_list": [
                "問、問我？",
                "問、問我？"
            ]
        },
        {
            "name": "醒目飛鷹",
            "text": "那還用說！訓練員也是\n飛飛重要的粉絲之一嘛♪"
        },
        {
            "name": "醒目飛鷹",
            "text": "你就別客氣了，好～好地……\n陪飛飛練習吧☆"
        },
        {
            "name": "獨白",
            "text": "後來，我便與醒目飛鷹\n一起構思了特別的姿勢。"
        }
    ]
}