{
    "no_wrap": true,
    "title": "情人節",
    "text_block_list": [
        {
            "name": "大德太陽",
            "text": "阿訓──！！\n這個巧克力不錯吧！？"
        },
        {
            "name": "獨白",
            "text": "時值情人節。是向照顧過自己的人和\n重要的人表達感謝之意的機會──"
        },
        {
            "name": "大德太陽",
            "text": "紅紅的很有大小姐的感覺吧！？\n還是莓果系的！超可愛！"
        },
        {
            "name": "獨白",
            "text": "大德太陽也不例外……\n因為她想送巧克力給第一紅寶，\n於是我便陪她一起挑選。"
        },
        {
            "name": "大德太陽",
            "text": "分量好像還很多呢！\n有多一點巧克力能吃也會比較開心吧？",
            "choice_data_list": [
                "她應該是重質不重量的類型吧",
                "她應該是重質不重量的類型吧"
            ]
        },
        {
            "name": "大德太陽",
            "text": "也對！！\n來問問專家吧！"
        },
        {
            "name": "大德太陽",
            "text": "請問！"
        },
        {
            "name": "店員",
            "text": "來了，請問有什──太、太陽！\n哇啊，我是妳的超級粉絲……！"
        },
        {
            "name": "大德太陽",
            "text": "真假？謝啦！\n現在有空嗎？"
        },
        {
            "name": "店員",
            "text": "請問需要什麼？"
        },
        {
            "name": "大德太陽",
            "text": "我想送我的好姐妹巧克力！\n然後她是個超級大小姐～"
        },
        {
            "name": "大德太陽",
            "text": "我一直以來都只是收禮！\n所以不太懂這些。\n然後，因為～那個……",
            "choice_data_list": [
                "妳想送她哪種巧克力呢？"
            ]
        },
        {
            "name": "大德太陽",
            "text": "對耶！"
        },
        {
            "name": "大德太陽",
            "text": "請給我\n會讓好姐妹喜翻上我的巧克力！"
        },
        {
            "name": "店員",
            "text": "我知道了！\n我會竭誠挑選！"
        },
        {
            "name": "大德太陽",
            "text": "謝謝！！"
        },
        {
            "name": "大德太陽",
            "text": "嘿嘿──♪\n好期待情人節！",
            "choice_data_list": [
                "能順利買到真是太好了",
                "能順利買到真是太好了"
            ]
        },
        {
            "name": "大德太陽",
            "text": "嗯！"
        },
        {
            "name": "大德太陽",
            "text": "大小姐會不會愛上我的品味啊？\n希望她會──！！"
        },
        {
            "name": "獨白",
            "text": "這時我突然浮現了一個單純的疑問。\n如果第一紅寶真的真的愛上了，\n大德太陽打算怎麼做呢？",
            "choice_data_list": [
                "太陽想跟紅寶成為什麼樣的關係呢？"
            ]
        },
        {
            "name": "大德太陽",
            "text": "什麼？"
        },
        {
            "name": "大德太陽",
            "text": "成為什麼樣，是什麼意思？\n什麼都不會改變吧？"
        },
        {
            "name": "大德太陽",
            "text": "好姐妹指的就是～\n最喜翻的人啊。"
        },
        {
            "name": "大德太陽",
            "text": "然後在最喜翻的人面前，\n不都會爆笑？？"
        },
        {
            "name": "大德太陽",
            "text": "就像我總是在阿訓還有死黨還有善善\n面前笑個不停，就是那樣！",
            "choice_data_list": [
                "如果兩情相悅，就能看見她的笑容……是嗎？"
            ]
        },
        {
            "name": "大德太陽",
            "text": "沒錯☆"
        },
        {
            "name": "大德太陽",
            "text": "我跟大小姐根本完全相反～\n這點我還是知道的！"
        },
        {
            "name": "大德太陽",
            "text": "雖然大小姐認為那是代表我們「不一樣」。\n不過我們只是相反，沒有不一樣吧？"
        },
        {
            "name": "大德太陽",
            "text": "她絕對能露出跟我一樣的笑臉的。\n絕──對！"
        },
        {
            "name": "獨白",
            "text": "大德太陽如此極力主張。\n如果對方收下了巧克力的話，\n應該能夠踏出縮短距離的第一步吧。",
            "choice_data_list": [
                "希望她收到巧克力會開心",
                "希望她收到巧克力會開心"
            ]
        },
        {
            "name": "大德太陽",
            "text": "嗯♪"
        },
        {
            "name": "獨白",
            "text": "然後到了情人節當天。\n我一邊祈禱著大德太陽能夠成功，\n一邊處理著工作──"
        },
        {
            "name": "大德太陽",
            "text": "被打槍了──！！",
            "choice_data_list": [
                "什麼！？"
            ]
        },
        {
            "name": "大德太陽",
            "text": "哭哭變爆哭變痛哭，\n冷冰冰的回答～～！！",
            "choice_data_list": [
                "……善信，發生什麼事了？"
            ]
        },
        {
            "name": "目白善信",
            "text": "嗯。\n剛才去送巧克力給紅寶的時候……"
        },
        {
            "name": "第一紅寶",
            "text": "──雖然非常過意不去，\n但我不能收下。"
        },
        {
            "name": "大德太陽",
            "text": "……咦？"
        },
        {
            "name": "大德太陽",
            "text": "咦咦咦咦咦咦咦咦咦！？\n為什麼！？"
        },
        {
            "name": "大德太陽",
            "text": "咦？妳不喜歡巧克力嗎？\n討厭甜食嗎？這樣的話──"
        },
        {
            "name": "第一紅寶",
            "text": "「一起在短距離嗨起來吧。」\n妳之前這樣跟我說過吧？"
        },
        {
            "name": "大德太陽",
            "text": "嗯！"
        },
        {
            "name": "大德太陽",
            "text": "因為大小姐也來這邊了嘛☆\n我還想說能不能一起創個太寶頻道呢♪"
        },
        {
            "name": "第一紅寶",
            "text": "我不是自願過來的，是墜落下來的。"
        },
        {
            "name": "大德太陽",
            "text": "什麼？"
        },
        {
            "name": "第一紅寶",
            "text": "不管怎樣，我會賭上自己的一切，\n在今後參加的所有比賽中留下成果。"
        },
        {
            "name": "第一紅寶",
            "text": "因此我不能接受妳的心意……\n不對，是不會接受。"
        },
        {
            "name": "第一紅寶",
            "text": "希望……\n妳能夠理解。"
        },
        {
            "name": "大德太陽",
            "text": "徹底地！！\n被打槍了──！！！！"
        },
        {
            "name": "目白善信",
            "text": "嗯……\n我覺得妳應該不是被打槍了。"
        },
        {
            "name": "目白善信",
            "text": "紅寶拒絕的，是跟妳一起嗨的這件事吧？"
        },
        {
            "name": "大德太陽",
            "text": "怎麼可能──！\n沒有人會討厭嗨起來吧。"
        },
        {
            "name": "目白善信",
            "text": "……我大概能稍微理解紅寶的心情。",
            "choice_data_list": [
                "可以說來聽聽嗎？",
                "可以說來聽聽嗎？"
            ]
        },
        {
            "name": "目白善信",
            "text": "就是，\n我好歹也是名門賽馬娘對吧？"
        },
        {
            "name": "目白善信",
            "text": "不過我卻都沒有參加\n像是經典三冠之類的主流競賽。"
        },
        {
            "name": "目白善信",
            "text": "雖然這都是我自己下的決定，\n但我偶爾還是會這樣想喔？"
        },
        {
            "name": "目白善信",
            "text": "要是我能回應大家的期待就好了，\n之類的。",
            "choice_data_list": [
                "善信……"
            ]
        },
        {
            "name": "目白善信",
            "text": "啊！\n不過我現在一點都不後悔喔！"
        },
        {
            "name": "目白善信",
            "text": "可是……或許紅寶並不是這樣。\n對她而言這可能不是個正向的選擇。"
        },
        {
            "name": "目白善信",
            "text": "即使如此她還是決定在這條路上繼續前進，\n一定是下了很大的決心吧。"
        },
        {
            "name": "目白善信",
            "text": "所以她才會表明決心，說她不會享受比賽吧。\n雖然都只是我自己的猜測啦。"
        },
        {
            "name": "大德太陽",
            "text": "……也就是說。\n善善，我……"
        },
        {
            "name": "目白善信",
            "text": "嗯。"
        },
        {
            "name": "大德太陽",
            "text": "其實還有機會嗎！？",
            "choice_data_list": [
                "真是正向！"
            ]
        },
        {
            "name": "目白善信",
            "text": "嗯！\n還有機會啦！！"
        },
        {
            "name": "大德太陽",
            "text": "好耶！！\n有機會────！",
            "choice_data_list": [
                "……妳真的有聽懂善信說的話嗎？"
            ]
        },
        {
            "name": "大德太陽",
            "text": "嗯！雖然不知道紅寶怎麼了，\n但她嗨不起來對吧？"
        },
        {
            "name": "大德太陽",
            "text": "那只要跟我一起跑就好了吧☆\n我超擅長嗨起來的！"
        },
        {
            "name": "大德太陽",
            "text": "話說現在要不要開派對？\n要不要開巧克力派對？畢竟今天是情人節嘛！"
        },
        {
            "name": "大德太陽",
            "text": "我也買了訓善的份喔！",
            "choice_data_list": [
                "什麼時候買的……！"
            ]
        },
        {
            "name": "大德太陽",
            "text": "這是企業機密！\n有點像是忍術那樣！"
        },
        {
            "name": "大德太陽",
            "text": "說是這麼說，\n但其實只是昨天偷偷跑去買的啦☆"
        },
        {
            "name": "目白善信",
            "text": "謝謝妳，太陽！"
        },
        {
            "name": "目白善信",
            "text": "當然，我也有準備喔！\n我選了一個最棒的巧克力！",
            "choice_data_list": [
                "我也有買喔",
                "我也有買唷"
            ]
        },
        {
            "name": "目白善信",
            "text": "不愧是訓練員！\n這樣就能開派對了呢！"
        },
        {
            "name": "大德太陽",
            "text": "有好麻吉&小訓真好～～！！"
        },
        {
            "name": "獨白",
            "text": "就這樣，\n我和完全恢復精神的大德太陽，\n以及目白善信一起開了一個小小的巧克力派對。"
        },
        {
            "name": "目白善信",
            "text": "喔──不錯耶！\n畢竟今天是難得的情人節嘛。",
            "choice_data_list": [
                "來辦派對吧"
            ]
        },
        {
            "name": "大德太陽",
            "text": "喔耶～！\n那就立刻開始！"
        },
        {
            "name": "獨白",
            "text": "雖然說是派對，\n但應該是像交換禮物之類的活動吧。"
        },
        {
            "name": "獨白",
            "text": "儘管我和目白善信跟大德太陽\n一起相處已經來到第三年。\n我們的想法還是太天真了──"
        },
        {
            "name": "大德太陽",
            "text": "──很好！！\n卯足全力上吧！！"
        },
        {
            "name": "太陽的朋友A",
            "text": "儘管來吧──！！"
        },
        {
            "name": "目白善信",
            "text": "太、太陽……這是什麼……？"
        },
        {
            "name": "大德太陽",
            "text": "是巧克力派對啊！\n「超巨大巧克力噴泉派對」！"
        },
        {
            "name": "獨白",
            "text": "大德太陽所準備的是……\n巨大到幾乎要碰到體育館天花板的\n巧克力噴水池！",
            "choice_data_list": [
                "這個，有獲得許可嗎……！？"
            ]
        },
        {
            "name": "大德太陽",
            "text": "理事長說──！",
            "choice_data_list": [
                "理事長！！"
            ],
            "color_text_info_list": [
                "理事長"
            ]
        },
        {
            "name": "大德太陽",
            "text": "可以站在樓梯間沾巧克力，\n也可以站在梯子上沾！"
        },
        {
            "name": "大德太陽",
            "text": "不過不可以游泳！！\n要珍惜食物！"
        },
        {
            "name": "大德太陽",
            "text": "啊，\n有特別的巧克力要給善善跟阿訓喔！"
        },
        {
            "name": "目白善信",
            "text": "欸，\n妳說的該不會是吊在天花板上的……"
        },
        {
            "name": "大德太陽",
            "text": "對！\n就是那個超級無敵大的愛心！",
            "choice_data_list": [
                "咦咦咦咦！？"
            ]
        },
        {
            "name": "獨白",
            "text": "大德太陽指著的前方……\n有個吊在天花板上的超巨大愛心。\n仔細一看包裝紙上寫著收件人的姓名。"
        },
        {
            "name": "目白善信",
            "text": "好大……"
        },
        {
            "name": "大德太陽",
            "text": "你們願意收下我的love嗎？"
        },
        {
            "name": "目白善信",
            "text": "唔！！"
        },
        {
            "name": "大德太陽",
            "text": "期待期待……"
        },
        {
            "name": "目白善信",
            "text": "……"
        },
        {
            "name": "目白善信",
            "text": "訓練員！",
            "choice_data_list": [
                "好，我要開動了！！",
                "嗯，我要開動了！！"
            ]
        },
        {
            "name": "目白善信",
            "text": "──肚、肚子好撐……",
            "choice_data_list": [
                "對啊……",
                "對呀……"
            ]
        },
        {
            "name": "大德太陽",
            "text": "嘻嘻嘻☆\n很幸福吧？"
        },
        {
            "name": "目白善信",
            "text": "呵呵……是啊，\n很幸福！"
        },
        {
            "name": "大德太陽",
            "text": "我也很幸福～☆"
        },
        {
            "name": "獨白",
            "text": "在這個情人節，\n我收到了大德太陽多到滿出來的愛。"
        }
    ]
}