{
    "no_wrap": true,
    "title": "天皇賞（秋）結束後．打破沉默的光芒",
    "text_block_list": [
        {
            "name": "獨白",
            "text": "跟無聲鈴鹿間的對決結束了，「天皇賞（秋）」\n也同時落幕。目白光明如太陽般綻放出強烈光輝，\n讓世間見識到目白家光芒之威名。"
        },
        {
            "name": "獨白",
            "text": "兩人互相讚賞對方的精彩表現，\n然後各自走上不同的道路。"
        },
        {
            "name": "獨白",
            "text": "目白光明的戰鬥尚未結束。\n她發誓將在年底的「有馬紀念」上\n讓目白家的光芒綻放得更加耀眼。",
            "color_text_info_list": [
                "有馬紀念"
            ]
        }
    ]
}