{
    "no_wrap": true,
    "title": "熱血喧鬧的賽馬娘！",
    "text_block_list": [
        {
            "name": "桐生院訓練員",
            "text": "<username>訓練員──\n你要不要成為賽馬娘！？",
            "choice_data_list": [
                "……什麼？"
            ]
        },
        {
            "name": "桐生院訓練員",
            "text": "啊，我這麼說太突然了對吧……？\n我的意思是指在遊戲裡變成賽馬娘。"
        },
        {
            "name": "桐生院訓練員",
            "text": "那邊那台完全沉浸式VR特殊機器\n「VR賽馬娘模擬器」新增了新的程式──"
        },
        {
            "name": "桐生院訓練員",
            "text": "據說是能夠透過賽馬娘的虛擬替身，\n來「體驗賽馬娘的能力」！",
            "choice_data_list": [
                "哦～確實是挺令人好奇的！"
            ]
        },
        {
            "name": "東海帝皇",
            "text": "也讓我加～入嘛♪\n玩遊戲吾是不會輸的～！"
        },
        {
            "name": "獨白",
            "text": "從我身旁突然出現的賽馬娘──\n東海帝皇站在VR賽馬娘模擬器前，\n熟練地進行操作。"
        },
        {
            "name": "東海帝皇",
            "text": "反正既然都要體驗了，在有真正的賽馬娘\n參加的情況下對戰看看比較好對吧～？\n我看看喔，現在能一起玩的只有鬼抓人──"
        },
        {
            "name": "東海帝皇",
            "text": "嗯，OK了！\n你就充當會長的角色吧！",
            "choice_data_list": [
                "我、我當魯道夫象徵……？",
                "我、我當魯道夫象徵……？"
            ]
        },
        {
            "name": "獨白",
            "text": "會長，\n也就是指「皇帝」魯道夫象徵，\n她是賽馬娘中以最強聞名的存在。"
        },
        {
            "name": "獨白",
            "text": "雖說是VR遊戲，\n但能親身體驗她能力的話，\n想必會對將來很有幫助吧……！",
            "choice_data_list": [
                "好！我就試試看吧！"
            ]
        },
        {
            "name": "溫順（桐生院）",
            "text": "！！\n<username>訓練員，\n你看起來就像魯道夫象徵本人一樣呢！"
        },
        {
            "name": "溫順（桐生院）",
            "text": "好驚人的還原度……！\n我也完全變成溫順了……！",
            "choice_data_list": [
                "桐生院訓練員為什麼會選擇這個虛擬替身呢？"
            ]
        },
        {
            "name": "溫順（桐生院）",
            "text": "……其實是因為我覺得她最近訓練的\n負擔似乎太大了。\n想透過體驗她的實際能力來調整訓練計畫──"
        },
        {
            "name": "東海帝皇",
            "text": "兩位～\n遊戲已經～開始……了喔！！"
        },
        {
            "name": "擴音器",
            "text": "「你現在是鬼。\n被東海帝皇碰觸到了。」",
            "choice_data_list": [
                "什麼時候！？"
            ]
        },
        {
            "name": "東海帝皇",
            "text": "真是的～竟然呆呆站著不動。\n這樣根本一點都不像會長嘛～♪",
            "choice_data_list": [
                "那……就等著看我的反擊！",
                "那……就等著看我的反擊！"
            ]
        },
        {
            "name": "東海帝皇",
            "text": "哎唷！太慢了太慢了！"
        },
        {
            "name": "溫順（in桐生院）",
            "text": "訓、訓練員！\n我們追上去吧！",
            "choice_data_list": [
                "好！！"
            ]
        },
        {
            "name": "獨白",
            "text": "儘管只是有樣學樣，但我照平常所見的\n印象調整好呼吸，並在腳底蓄力。\n接著盯緊了位在遠方的東海帝皇──",
            "choice_data_list": [
                "唔喔喔喔喔喔喔喔喔！",
                "呀啊啊啊啊啊啊啊啊！"
            ]
        },
        {
            "name": "東海帝皇",
            "text": "唔哇哇哇哇！？\n好快──！"
        },
        {
            "name": "擴音器",
            "text": "「你碰觸到了東海帝皇。\n接下來由東海帝皇當鬼。」"
        },
        {
            "name": "東海帝皇",
            "text": "什、什什麼……！\n剛剛那是怎樣──",
            "choice_data_list": [
                "這就是魯道夫象徵的腳力……！"
            ]
        },
        {
            "name": "擴音器",
            "text": "「東海帝皇現在是鬼。\n五分鐘內沒有碰觸到他人將判定敗北。」"
        },
        {
            "name": "東海帝皇",
            "text": "咦咦～～！不要不要！\n我不想要輸～～～啦～～～！！"
        },
        {
            "name": "東海帝皇",
            "text": "唔唔唔……我不會再大意了！\n我要開始認真了哦！？",
            "choice_data_list": [
                "正合我意！！",
                "正合我意！！"
            ]
        },
        {
            "name": "獨白",
            "text": "於是，直到遊戲時間結束為止，\n我們一直專注於這場令人重返童心的鬼抓人。"
        },
        {
            "name": "東海帝皇",
            "text": "勉、勉強贏了……！",
            "choice_data_list": [
                "要是我能更加發揮出魯道夫的腳力……！"
            ]
        },
        {
            "name": "桐生院訓練員",
            "text": "呵呵。\n溫順的腳力也非常地強勁……\n透過這次體驗，讓我更了解她的能力了！",
            "choice_data_list": [
                "這樣啊！那我應該還是要選專任的──",
                "這樣啊！那我應該還是要選專任的──"
            ]
        },
        {
            "name": "東海帝皇",
            "text": "……你要用<chrname>的狀態，\n再跟我比一場嗎？",
            "choice_data_list": [
                "……是啊，我不會再讓妳贏了",
                "……嗯，我不會再讓妳贏了"
            ]
        },
        {
            "name": "東海帝皇",
            "text": "啊哈哈──很敢說嘛！"
        }
    ]
}