{
    "no_wrap": true,
    "title": "前往恐懼的旅程",
    "text_block_list": [
        {
            "name": "獨白",
            "text": "我與葛城榮主一同外出，\n在回程路上發生了一件事。"
        },
        {
            "name": "葛城榮主",
            "text": "我說，訓練員，接下來\n要不要去一個可以體驗恐懼的地方？",
            "choice_data_list": [
                "怎麼這麼突然？",
                "怎麼這麼突然？"
            ]
        },
        {
            "name": "葛城榮主",
            "text": "其實在不久之前──"
        },
        {
            "name": "葛城榮主",
            "text": "好，上吧！就是那裡！\n閃過前方──喂，妳為什麼不上！？"
        },
        {
            "name": "葛城榮主",
            "text": "哎呀……輸了。"
        },
        {
            "name": "賽馬娘A",
            "text": "呼、呼……可惡……！\n明明是很重要的模擬賽，我卻輸了……\n最後要是我能毫不畏懼地上前就好了……！"
        },
        {
            "name": "魯道夫象徵",
            "text": "不必感到後悔，因為妳知道自己退縮的原因了。\n妳可以說是成長了一步。"
        },
        {
            "name": "魯道夫象徵",
            "text": "透過了解自己的恐懼，\n我們可以變得更強大。"
        },
        {
            "name": "魯道夫象徵",
            "text": "反求諸己，面對自己的恐懼。\n當妳克服恐懼之後，榮耀就在前方等著妳。\n妳一定能夠克服的，我會幫妳加油。"
        },
        {
            "name": "賽馬娘A",
            "text": "會長……！謝謝妳！\n我會加油的！！"
        },
        {
            "name": "葛城榮主",
            "text": "喂，魯道夫，妳剛剛說……\n了解恐懼的話就會變強，那是什麼意思？"
        },
        {
            "name": "魯道夫象徵",
            "text": "啊啊…………沒事。"
        },
        {
            "name": "魯道夫象徵",
            "text": "這件事我沒辦法指導妳，\n因為妳的恐懼只有妳自己知道。"
        },
        {
            "name": "葛城榮主",
            "text": "就是這樣──\n拜託了！請幫幫我！"
        },
        {
            "name": "葛城榮主",
            "text": "我想了解恐懼，變得更強！！",
            "choice_data_list": [
                "原來是這樣，我願意幫忙"
            ]
        },
        {
            "name": "葛城榮主",
            "text": "──這就是最近傳聞中的靈異景點！",
            "choice_data_list": [
                "靈異景點……！"
            ]
        },
        {
            "name": "葛城榮主",
            "text": "沒錯！為了打聽出地點真是費了我一番功夫啊。\n大家都說一提到就會被詛咒，\n嚇得不跟我說。"
        },
        {
            "name": "葛城榮主",
            "text": "我記得這裡的傳聞是……神社的鈴鐺會擅自響起。\n以這個為訊號──屋簷下會出現老婆婆，\n然後看見老婆婆的人靈魂會被奪走。"
        },
        {
            "name": "獨白",
            "text": "（噹啷……噹啷……）",
            "choice_data_list": [
                "咿！！"
            ]
        },
        {
            "name": "葛城榮主",
            "text": "啊哈哈！你那是什麼叫聲！"
        },
        {
            "name": "葛城榮主",
            "text": "……咦？訓練員，\n你該不會很害怕吧？真的嗎？"
        },
        {
            "name": "葛城榮主",
            "text": "什麼，你害怕什麼！？為什麼害怕？\n快告訴我！",
            "choice_data_list": [
                "鈴鐺自己動起來……"
            ]
        },
        {
            "name": "葛城榮主",
            "text": "鈴鐺？可是那個鈴鐺掛得這麼隨便，\n只要風一吹就會響吧？",
            "choice_data_list": [
                "傳聞中鈴鐺一響，老婆婆就會出現……"
            ]
        },
        {
            "name": "葛城榮主",
            "text": "啊啊，原來如此……不過沒看到老婆婆啊。\n……那你是在害怕什麼……？"
        },
        {
            "name": "葛城榮主",
            "text": "嗯──抱歉，我真的不太懂！\n去下一個地方吧！"
        },
        {
            "name": "葛城榮主",
            "text": "這裡是被評為最恐怖的靈異景點！"
        },
        {
            "name": "葛城榮主",
            "text": "……爬上樓梯時，會從背後吹來\n一陣溫熱的風，轉頭的瞬間──\n會出現渾身是血的女人把你推下高塔！"
        },
        {
            "name": "獨白",
            "text": "（咻………………）",
            "choice_data_list": [
                "呀啊！？"
            ]
        },
        {
            "name": "葛城榮主",
            "text": "嗯？啊啊，那是從冷氣室外機吹出來的風吧，\n有點溫溫的吧？",
            "choice_data_list": [
                "……咦？"
            ]
        },
        {
            "name": "獨白",
            "text": "我環顧四周，確實有冷氣室外機。\n如果那就是熱風來源的話，\n或許就不是什麼靈異現象了……"
        },
        {
            "name": "葛城榮主",
            "text": "剛剛那陣風讓你很害怕吧？",
            "choice_data_list": [
                "……是啊",
                "……是呀"
            ]
        },
        {
            "name": "葛城榮主",
            "text": "然後呢？是為什麼害怕？\n你想像了一個渾身是血的女人嗎？",
            "choice_data_list": [
                "我覺得不恐怖了"
            ]
        },
        {
            "name": "葛城榮主",
            "text": "咦咦！？為什麼啊？\n你剛剛不是還在害怕嗎！"
        },
        {
            "name": "獨白",
            "text": "我告訴她，因為葛城榮主的正經評論，\n消除了我的恐懼感。"
        },
        {
            "name": "葛城榮主",
            "text": "你說什麼！？\n我明明只是在提問而已耶……！？"
        },
        {
            "name": "葛城榮主",
            "text": "啊～我只是想知道\n自己的恐懼而已啊！"
        },
        {
            "name": "葛城榮主",
            "text": "我想了解恐懼，變得更強！！",
            "choice_data_list": [
                "再試試看別的恐怖吧",
                "還是別想太多比較好"
            ]
        },
        {
            "name": "葛城榮主",
            "text": "別的啊……也是呢，\n恐怖也有很多種類呢。"
        },
        {
            "name": "葛城榮主",
            "text": "小丑，數字，饅頭之類的……\n全都試試看吧！"
        },
        {
            "name": "葛城榮主",
            "text": "很好！等著我吧恐懼！\n我絕對會感受到你的！！"
        },
        {
            "name": "獨白",
            "text": "她就這樣展開了\n理解恐懼的旅程。"
        },
        {
            "name": "葛城榮主",
            "text": "不思考就意味著放棄思考。\n也就是說，這和逃跑是一樣的！"
        },
        {
            "name": "葛城榮主",
            "text": "我只會在賽場上逃離競爭者的追趕。\n除此之外我都不想逃跑！"
        },
        {
            "name": "葛城榮主",
            "text": "我要朝著恐懼邁進！\n絕不放棄！"
        },
        {
            "name": "獨白",
            "text": "她就這樣展開了\n理解恐懼的旅程。"
        }
    ]
}