{
    "no_wrap": true,
    "title": "好痛",
    "text_block_list": [
        {
            "name": "醫生",
            "text": "真是的，竟然在這種狀態的腳趾甲上，\n貼上人工甲片……"
        },
        {
            "name": "島川喬登",
            "text": "……"
        },
        {
            "text": "島川喬登的腳趾甲\n已經裂到了深處，變成了紅黑色。",
            "choice_data_list": [
                "這是……"
            ]
        },
        {
            "name": "島川喬登",
            "text": "可是我能跑！！\n我可以跑！！"
        },
        {
            "name": "醫生",
            "text": "……別因為是腳趾甲就小看它。"
        },
        {
            "name": "醫生",
            "text": "妳們賽馬娘每次比賽時，\n腳部都會承受，\n我們人類根本無法相比的負荷。"
        },
        {
            "name": "醫生",
            "text": "即使想靠拇趾球承受地面的反作用力，\n但妳的腳尖……\n腳趾甲承受的負荷仍不容小覷。"
        },
        {
            "name": "島川喬登",
            "text": "……可是，只要纏運動貼布……！"
        },
        {
            "name": "醫生",
            "text": "要是因為勉強跑步而細菌感染呢？\n要是跑步時顧慮腳尖，\n造成其他部位受傷呢？"
        },
        {
            "name": "醫生",
            "text": "實際上\n這次妳不就痛到無法忍受了嗎？"
        },
        {
            "name": "島川喬登",
            "text": "……！"
        },
        {
            "name": "醫生",
            "text": "僅僅一個選擇，\n就可能賠上\n妳今後的人生喔。"
        },
        {
            "name": "島川喬登",
            "text": "…………"
        },
        {
            "text": "以防萬一，我們拿了醫生開的藥，\n然後離開了醫院。"
        },
        {
            "name": "島川喬登",
            "text": "……",
            "choice_data_list": [
                "腳會痛嗎？",
                "腳會痛嗎？"
            ]
        },
        {
            "name": "島川喬登",
            "text": "……我要參加「皋月賞」。",
            "choice_data_list": [
                "這……"
            ]
        },
        {
            "name": "島川喬登",
            "text": "我已經決定了！\n之後不管怎樣都沒關係！\n我一定要跑「皋月賞」！！"
        },
        {
            "name": "島川喬登",
            "text": "不然……我就不跑步了！\n不能跑那場比賽，我就直接引退！！"
        },
        {
            "name": "島川喬登",
            "text": "因為！這可是一輩子只有一次的機會喔？\n如果又要因為腳趾甲的關係放棄……"
        },
        {
            "name": "教官A",
            "text": "咦。喬登，妳的腳趾甲又……？\n……那這次的選拔賽也得放棄了。"
        },
        {
            "name": "教官A",
            "text": "不過沒關係的。只要夠努力，\n從現在開始也一定能追上同期選手──"
        },
        {
            "name": "教官A",
            "text": "這樣啊，腳趾甲又裂了嗎。\n這次是因為過度練跑…………"
        },
        {
            "name": "教官A",
            "text": "……欸，妳可以跟老師說嗎？\n妳的真心話之類……？"
        },
        {
            "name": "教官A",
            "text": "聽說喬登的腳趾甲這次又裂了。\n嗯，是……這樣一來，\n也不好推薦她參加選拔賽呢。"
        },
        {
            "name": "教官B",
            "text": "是啊……這次受傷的事也是她自己上報的吧？\n也不知道那個傷到底是不是真的，\n都已經有傳聞了……"
        },
        {
            "name": "教官A",
            "text": "……是啊。唉……如果她不想跑，\n要是好好跟我商量的話，\n我會幫忙的說……"
        },
        {
            "name": "島川喬登",
            "text": "我……我……！\n我不想再失去比賽了！！"
        },
        {
            "name": "島川喬登",
            "text": "我從以前就不會唸書！又笨拙！\n還會被老師罵得慘兮兮！！"
        },
        {
            "name": "島川喬登",
            "text": "原本以為終於能一直贏、一直贏、一直贏下去！\n成為了不起的人物……！\n但是……！"
        },
        {
            "name": "島川喬登",
            "text": "這一切都要被腳趾甲奪走了……！\n被人說我連經典賽都不能跑……"
        },
        {
            "name": "島川喬登",
            "text": "我這樣下去……\n根本無法實現夢想嘛……！"
        },
        {
            "name": "島川喬登",
            "text": "我已經受不了了……！！\n受不了了……！",
            "choice_data_list": [
                "喬登……"
            ]
        },
        {
            "name": "島川喬登",
            "text": "……"
        },
        {
            "text": "……泫然欲泣的她眼中含著淚水……\n含著她的不甘。",
            "choice_data_list": [
                "那妳能夠「忍耐」嗎？",
                "那妳能夠「忍耐」嗎？"
            ]
        },
        {
            "name": "島川喬登",
            "text": "當然可以！這點痛楚……！",
            "choice_data_list": [
                "我指的不是痛楚"
            ]
        },
        {
            "text": "就算帶傷出場，\n也只會縮短她的賽跑生涯。"
        },
        {
            "text": "但在那之前，要是把可能性這選項奪走的話，\n會讓她的心一蹶不振吧。\n既然這樣──"
        },
        {
            "text": "至少要讓她比現在更細心照護腳趾甲。\n運動鞋方面，我來找找有沒有辦法，\n可以幫她進行改善吧。"
        },
        {
            "text": "要將她的腳放第一……\n並且為了獲勝也要繼續訓練。",
            "choice_data_list": [
                "妳會失去休閒娛樂的時間喔",
                "妳會失去休閒娛樂的時間喔"
            ]
        },
        {
            "name": "島川喬登",
            "text": "…………！",
            "choice_data_list": [
                "妳有把一切都賭在比賽上的決心嗎？",
                "妳有把一切都賭在比賽上的決心嗎？"
            ]
        },
        {
            "name": "島川喬登",
            "text": "……"
        },
        {
            "name": "島川喬登",
            "text": "我有。這還用問嗎。"
        },
        {
            "name": "島川喬登",
            "text": "我也會成為偉大的選手！\n我一定要去比賽",
            "choice_data_list": [
                "下次覺得痛的時候，希望妳立刻找我商量"
            ]
        },
        {
            "name": "島川喬登",
            "text": "……！\n…………"
        },
        {
            "name": "島川喬登",
            "text": "……嗯。"
        },
        {
            "name": "島川喬登",
            "text": "……抱歉我一直瞞著你。"
        },
        {
            "name": "戴獵帽的記者",
            "text": "她、她沒事吧！？\n訓練員！",
            "choice_data_list": [
                "嗯，她暫時沒有大礙"
            ]
        },
        {
            "name": "戴獵帽的記者",
            "text": "這樣啊……太好了～\n可是那個傷讓她很痛苦的樣子，\n「皋月賞」果然──",
            "choice_data_list": [
                "等等，關於這件事──"
            ]
        },
        {
            "text": "我懇求記者\n別將他在這次訓練中看到的事寫成報導。"
        },
        {
            "text": "我跟他說：「不希望在皋月賞前\n出現令人不安的報導，造成不必要的騷動。」"
        },
        {
            "name": "戴獵帽的記者",
            "text": "……你的意思是……\n要逼迫為傷勢而苦的賽馬娘去比賽嗎？"
        },
        {
            "name": "戴獵帽的記者",
            "text": "這件事……恕我無法答應。\n我也是做報導的。\n如果訓練員你打算強迫她……"
        },
        {
            "name": "島川喬登",
            "text": "不是的！他才不會做這種事咧！\n我們已經約好要把腳趾甲治好了！！"
        },
        {
            "name": "島川喬登",
            "text": "所以拜託……請答應我們！\n為了我的「皋月賞」……\n請幫幫我……！！",
            "choice_data_list": [
                "……拜託你"
            ]
        },
        {
            "name": "戴獵帽的記者",
            "text": "……"
        },
        {
            "name": "戴獵帽的記者",
            "text": "……我知道了。\n剛才的事目前我只會記在心裡的。"
        },
        {
            "name": "島川喬登",
            "text": "…………",
            "choice_data_list": [
                "繼續加油吧"
            ]
        },
        {
            "name": "島川喬登",
            "text": "……嗯。"
        },
        {
            "name": "島川喬登",
            "text": "…………謝謝你，訓練員。"
        },
        {
            "text": "從這天起，以「皋月賞」為目標，\n一邊照顧腳傷一邊調整的日子\n就此展開──"
        }
    ]
}